odeopt/__about__.py
odeopt/__init__.py
odeopt/core/__init__.py
odeopt/core/data.py
odeopt/core/utils.py
odeopt/model/__init__.py
odeopt/model/init_model.py
odeopt/model/ode_model.py
odeopt/model/param_model.py
odeopt/ode/__init__.py
odeopt/ode/solver/__init__.py
odeopt/ode/solver/odesolver.py
odeopt/ode/system/__init__.py
odeopt/ode/system/linearsys.py
odeopt/ode/system/nonlinearsys.py
odeopt/ode/system/odesys.py
odeopt-0.1.2.dist-info/AUTHORS.rst
odeopt-0.1.2.dist-info/LICENSE
odeopt-0.1.2.dist-info/METADATA
odeopt-0.1.2.dist-info/WHEEL
odeopt-0.1.2.dist-info/top_level.txt
odeopt-0.1.2.dist-info/RECORD
